<?xml version="1.0"?>
<EmbeddedProfile xmlns:xsi="http://www.w3.org/2001/XMLSchema-instance" xmlns:xsd="http://www.w3.org/2001/XMLSchema">
  <ToolchainID>d63903af-7af9-4be7-ad99-d371ba7d7b7a</ToolchainID>
  <ToolchainVersion>
    <GCC>11.1.0</GCC>
    <GDB>10.2</GDB>
    <Revision>0</Revision>
  </ToolchainVersion>
  <BspID>com.sysprogs.avr.core</BspID>
  <BspVersion>1.0</BspVersion>
  <McuID>ATMEGA32U4</McuID>
  <MCUDefinitionFile>DeviceDefinitions/atmega32u4.xml</MCUDefinitionFile>
  <MCUProperties>
    <Entries />
  </MCUProperties>
  <BSPSourceFolderName>Device-specific files</BSPSourceFolderName>
  <MCUMakFile>avr.mak</MCUMakFile>
  <ReferencedFrameworks />
  <FrameworkProperties>
    <Entries />
  </FrameworkProperties>
  <TestFrameworkProperties>
    <Entries />
  </TestFrameworkProperties>
</EmbeddedProfile>